{
  "f9659071-3713-4d7a-9ecd-f2d88b019dc6": {
    "id": "f9659071-3713-4d7a-9ecd-f2d88b019dc6",
    "newOrder": [
      {
        "id": "4c43ce4e-1b89-471c-9461-23ac902dbeee",
        "name": "Очки",
        "price": 100,
        "packageAmount": 1,
        "amount": 1,
        "totalSum": 100
      }
    ],
    "name": "Олег",
    "phone": "123",
    "comment": "",
    "total": 100,
    "time": "12.07.2020, 13:04:50"
  },
  "29389574-6a23-4228-afee-93d0d4fac1fe": {
    "id": "29389574-6a23-4228-afee-93d0d4fac1fe",
    "newOrder": [],
    "name": "ыв",
    "phone": "",
    "comment": "",
    "total": 0,
    "time": "12.07.2020, 13:05:39"
  },
  "3ed02160-eeb5-4ebc-aaac-a8799f710929": {
    "id": "3ed02160-eeb5-4ebc-aaac-a8799f710929",
    "newOrder": [
      {
        "id": "2e6f7bd4-eabe-47a2-b35e-e500f1cffcbd",
        "name": "Катлеты",
        "price": 221,
        "packageAmount": 12,
        "amount": 12,
        "totalSum": 2652
      },
      {
        "id": "e04f0bf6-e8ff-4ab6-89dd-2b416b397af1",
        "name": "Морс",
        "price": 2,
        "packageAmount": 2,
        "amount": 4,
        "totalSum": 8
      }
    ],
    "name": "вфыв",
    "phone": "фыв",
    "comment": "",
    "total": 2660,
    "time": "12.07.2020, 13:06:07"
  },
  "14d6528e-841e-452a-b5e8-84cbae6639cc": {
    "id": "14d6528e-841e-452a-b5e8-84cbae6639cc",
    "newOrder": [
      {
        "id": "2e6f7bd4-eabe-47a2-b35e-e500f1cffcbd",
        "name": "Катлеты",
        "price": 221,
        "packageAmount": 12,
        "amount": 12,
        "totalSum": 2652
      },
      {
        "id": "e04f0bf6-e8ff-4ab6-89dd-2b416b397af1",
        "name": "Морс",
        "price": 2,
        "packageAmount": 2,
        "amount": 4,
        "totalSum": 8
      }
    ],
    "name": "Max",
    "phone": "",
    "comment": "",
    "total": 2660,
    "time": "12.07.2020, 13:24:15"
  },
  "d7e9e459-ddcc-4514-a79c-71f328a57945": {
    "id": "d7e9e459-ddcc-4514-a79c-71f328a57945",
    "newOrder": [
      {
        "id": "e04f0bf6-e8ff-4ab6-89dd-2b416b397af1",
        "name": "Морс",
        "price": 2,
        "packageAmount": 2,
        "amount": 4,
        "totalSum": 8
      }
    ],
    "name": "",
    "phone": "",
    "comment": "",
    "total": 8,
    "time": "12.07.2020, 13:25:12"
  },
  "9f630a43-6cc6-4222-be9a-482ca15e32a7": {
    "id": "9f630a43-6cc6-4222-be9a-482ca15e32a7",
    "newOrder": [
      {
        "id": "1",
        "name": "Фарш",
        "price": 100,
        "packageAmount": 100,
        "amount": 100,
        "totalSum": 10000
      }
    ],
    "name": "Фарш",
    "phone": "",
    "comment": "",
    "total": 10000,
    "time": "12.07.2020, 13:29:23"
  },
  "2ef41f96-2e15-4a12-8b4e-722cc6db686d": {
    "id": "2ef41f96-2e15-4a12-8b4e-722cc6db686d",
    "newOrder": [
      {
        "id": "2e6f7bd4-eabe-47a2-b35e-e500f1cffcbd",
        "name": "Катлеты",
        "price": 221,
        "packageAmount": 12,
        "amount": 396,
        "totalSum": 87516
      },
      {
        "id": "e04f0bf6-e8ff-4ab6-89dd-2b416b397af1",
        "name": "Морс",
        "price": 2,
        "packageAmount": 2,
        "amount": 8,
        "totalSum": 16
      },
      {
        "id": "4c43ce4e-1b89-471c-9461-23ac902dbeee",
        "name": "Очки",
        "price": 100,
        "packageAmount": 1,
        "amount": 10,
        "totalSum": 1000
      }
    ],
    "name": "Максим",
    "phone": "1231231231",
    "comment": "Хочу быстро",
    "total": 88532,
    "time": "12.07.2020, 13:31:39"
  }
}